{
  "$schema": "https://developer.microsoft.com/json-schemas/fabric/item/report/definition/visualContainer/2.10.0/schema.json",
  "name": "ac53b4cb9985b52d511f",
  "position": {
    "x": 10.041950422228275,
    "y": 0,
    "z": 0,
    "height": 50.209752111141377,
    "width": 1252.7333151729772,
    "tabOrder": 0
  },
  "visual": {
    "visualType": "textbox",
    "objects": {
      "general": [
        {
          "properties": {
            "paragraphs": [
              {
                "textRuns": [
                  {
                    "value": "User Analysis",
                    "textStyle": {
                      "fontWeight": "bold",
                      "fontSize": "18pt",
                      "color": "#e66c37"
                    }
                  }
                ],
                "horizontalTextAlignment": "center"
              }
            ]
          }
        }
      ]
    },
    "drillFilterOtherVisuals": true
  }
}