{
  "$schema": "https://developer.microsoft.com/json-schemas/fabric/item/report/definition/visualContainer/2.10.0/schema.json",
  "name": "32334705f11893c19f3b",
  "position": {
    "x": 0,
    "y": 255.83215431864454,
    "z": 5,
    "height": 45.229994133683007,
    "width": 521.55836985403221,
    "tabOrder": 5
  },
  "visual": {
    "visualType": "textbox",
    "objects": {
      "general": [
        {
          "properties": {
            "paragraphs": [
              {
                "textRuns": [
                  {
                    "value": "Access Requests Over Time",
                    "textStyle": {
                      "fontWeight": "bold",
                      "fontFamily": "Arial Black",
                      "fontSize": "16pt",
                      "color": "#e66c37"
                    }
                  }
                ]
              }
            ]
          }
        }
      ]
    },
    "drillFilterOtherVisuals": true
  }
}